{
  "id": "dante",
  "title": "但丁的流放之路",
  "heading": "但丁的流放之路",
  "kicker": "真实山河 · 放逐与神曲 · 从佛罗伦萨到拉文纳",
  "subtitle": "被故乡放逐的诗人，在漂泊的途中写下了整个来世",
  "seal": "但",
  "searchPlaceholder": "佛罗伦萨、维罗纳、拉文纳、神曲",
  "loaderText": "正在载入北意大利山河与但丁的流放节点",
  "bounds": [[8, 40], [16, 47]],
  "types": {
    "home": {
      "label": "故土",
      "color": "#2f6d5b"
    },
    "turning": {
      "label": "转折",
      "color": "#8f5d14"
    },
    "exile": {
      "label": "放逐",
      "color": "#9c2f1b"
    },
    "final": {
      "label": "终局",
      "color": "#7d3424"
    }
  },
  "points": [
    {
      "id": "florence",
      "name": "佛罗伦萨",
      "short": "佛罗伦萨",
      "years": "1265-1302",
      "type": "home",
      "lnglat": [11.255, 43.77],
      "summary": "但丁生于佛罗伦萨，自幼爱慕贝雅特丽齐，她成为《神曲》中引他升入天堂的灵魂。他深陷圭尔夫党争，最终在政治倾轧中被逐出故乡，终身未归。",
      "quote": "在我们人生旅途的中途，我发现自己迷失在一座幽暗的森林。",
      "works": ["《神曲》", "贝雅特丽齐"],
      "poem": "神曲·地狱篇·开篇",
      "importance": 5
    },
    {
      "id": "rome",
      "name": "罗马",
      "short": "罗马",
      "years": "1300-1301",
      "type": "turning",
      "lnglat": [12.496, 41.903],
      "summary": "1300 年的大赦圣年，正是《神曲》那场穿越来世之旅设定的时间。次年但丁出使教廷期间，佛罗伦萨发生政变，他被缺席判处流放——从此再未踏上故乡的土地。",
      "quote": "他为城邦出使罗马，归来时，故乡的大门已在身后永远关上。",
      "works": ["1300 大赦圣年", "缺席流放"],
      "importance": 4
    },
    {
      "id": "arezzo",
      "name": "阿雷佐",
      "short": "阿雷佐",
      "years": "1302-1304",
      "type": "exile",
      "lnglat": [11.88, 43.46],
      "summary": "流放之初，但丁栖身阿雷佐，与同被放逐的白党人为伍，谋划返乡而不得。漂泊的生涯，从托斯卡纳的这座小城正式开始。",
      "quote": "走出地狱，他抬头重新望见了满天繁星。",
      "works": ["流放之始", "白党流亡"],
      "importance": 4
    },
    {
      "id": "lucca",
      "name": "卢卡",
      "short": "卢卡",
      "years": "约1308",
      "type": "exile",
      "lnglat": [10.503, 43.843],
      "summary": "但丁辗转于托斯卡纳与北意大利诸城之间，卢卡是其中一站。寄人篱下的岁月里，《神曲》在颠沛中一篇篇成形。",
      "quote": "没有城邦再属于他，他便把整个宇宙写成自己的家。",
      "works": ["漂泊托斯卡纳", "客居诸城"],
      "importance": 4
    },
    {
      "id": "verona",
      "name": "维罗纳",
      "short": "维罗纳",
      "years": "约1312-1318",
      "type": "exile",
      "lnglat": [10.99, 45.44],
      "summary": "在维罗纳，但丁受大斯卡拉家族坎格兰德的庇护，度过流放中相对安定的岁月。正是在这里，他写下了关于放逐之苦最沉痛的诗行。",
      "quote": "你将尝到，别人的面包多么咸涩；上下别人的楼梯，是多么艰难的路。",
      "works": ["坎格兰德的庇护", "放逐预言"],
      "poem": "神曲·天堂篇·放逐预言",
      "importance": 5
    },
    {
      "id": "ravenna",
      "name": "拉文纳",
      "short": "拉文纳",
      "years": "1318-1321",
      "type": "final",
      "lnglat": [12.20, 44.42],
      "summary": "在拉文纳波伦塔家族的庇护下，但丁完成了《天堂篇》，为整部《神曲》画上句点。1321 年他染疟疾去世，长眠于此，再未回到佛罗伦萨。",
      "quote": "是爱，推动着太阳和群星。",
      "works": ["完成《天堂篇》", "1321 年长眠"],
      "poem": "神曲·三篇终章·群星",
      "importance": 5
    }
  ]
}
